ton_fragment/__init__.py
ton_fragment/helpers/__init__.py
ton_fragment/helpers/scraper.py
ton_fragment/models/__init__.py
ton_fragment/models/auction_item.py
ton_fragment/models/sale_item.py
ton_fragment/models/sold_item.py
ton_fragment/numbers/__init__.py
ton_fragment/numbers/bid.py
ton_fragment/numbers/bid_history.py
ton_fragment/numbers/history.py
ton_fragment/numbers/information.py
ton_fragment/numbers/number.py
ton_fragment/numbers/numbers.py
ton_fragment/numbers/ownership.py
ton_fragment/numbers/ownership_history.py
ton_fragment/usernames/__init__.py
ton_fragment/usernames/usernames.py
ton_fragment-1.0.3.dist-info/LICENSE
ton_fragment-1.0.3.dist-info/METADATA
ton_fragment-1.0.3.dist-info/WHEEL
ton_fragment-1.0.3.dist-info/top_level.txt
ton_fragment-1.0.3.dist-info/RECORD
