Metadata-Version: 2.1
Name: ton-fragment
Version: 1.0.3
Summary: UnOfficial Fragment (Telegram - Ton Coin) Python library
Home-page: https://github.com/iw4p/Ton-Fragment
Author: Nima Akbarzadeh
Author-email: iw4p@protonmail.com
Project-URL: Bug Tracker, https://github.com/iw4p/Ton-Fragment/issues
Project-URL: repository, https://github.com/iw4p/Ton-Fragment
Classifier: Programming Language :: Python :: 3
Classifier: License :: OSI Approved :: MIT License
Classifier: Operating System :: OS Independent
Requires-Python: >=3.6
License-File: LICENSE
Requires-Dist: requests
Requires-Dist: beautifulsoup4
